{"box_data": [{"position": {"minX": 559.0, "minY": 61.40625, "maxX": 620.0, "maxY": 154.625}, "class_id": 60, "box_caption": "phone 0.421", "scores": {"class_score": 0.420654296875}, "domain": "pixel"}, {"position": {"minX": 161.75, "minY": 59.4375, "maxX": 231.0, "maxY": 169.0}, "class_id": 60, "box_caption": "phone 0.373", "scores": {"class_score": 0.37255859375}, "domain": "pixel"}, {"position": {"minX": 507.0, "minY": 59.28125, "maxX": 565.0, "maxY": 149.25}, "class_id": 60, "box_caption": "phone 0.371", "scores": {"class_score": 0.37109375}, "domain": "pixel"}, {"position": {"minX": 31.90625, "minY": 32.46875, "maxX": 118.0, "maxY": 140.5}, "class_id": 60, "box_caption": "phone 0.343", "scores": {"class_score": 0.342529296875}, "domain": "pixel"}, {"position": {"minX": 98.625, "minY": 54.65625, "maxX": 176.125, "maxY": 156.375}, "class_id": 60, "box_caption": "phone 0.311", "scores": {"class_score": 0.311279296875}, "domain": "pixel"}, {"position": {"minX": 225.875, "minY": 57.59375, "maxX": 296.75, "maxY": 163.625}, "class_id": 60, "box_caption": "phone 0.261", "scores": {"class_score": 0.260986328125}, "domain": "pixel"}, {"position": {"minX": 511.5, "minY": 62.25, "maxX": 614.5, "maxY": 150.875}, "class_id": 60, "box_caption": "phone 0.235", "scores": {"class_score": 0.234619140625}, "domain": "pixel"}, {"position": {"minX": 354.75, "minY": 49.96875, "maxX": 407.75, "maxY": 161.875}, "class_id": 60, "box_caption": "phone 0.218", "scores": {"class_score": 0.2178955078125}, "domain": "pixel"}, {"position": {"minX": 406.5, "minY": 53.0625, "maxX": 457.5, "maxY": 153.75}, "class_id": 60, "box_caption": "phone 0.214", "scores": {"class_score": 0.213623046875}, "domain": "pixel"}, {"position": {"minX": 454.25, "minY": 50.5625, "maxX": 512.5, "maxY": 149.75}, "class_id": 60, "box_caption": "phone 0.210", "scores": {"class_score": 0.2099609375}, "domain": "pixel"}, {"position": {"minX": 362.25, "minY": 85.625, "maxX": 398.75, "maxY": 115.375}, "class_id": 60, "box_caption": "phone 0.145", "scores": {"class_score": 0.145263671875}, "domain": "pixel"}, {"position": {"minX": 561.0, "minY": 61.78125, "maxX": 620.0, "maxY": 156.125}, "class_id": 442, "box_caption": "mouse 0.125", "scores": {"class_score": 0.12457275390625}, "domain": "pixel"}, {"position": {"minX": 314.75, "minY": 96.1875, "maxX": 331.75, "maxY": 111.0625}, "class_id": 243, "box_caption": "button 0.122", "scores": {"class_score": 0.1217041015625}, "domain": "pixel"}, {"position": {"minX": 559.0, "minY": 61.40625, "maxX": 620.0, "maxY": 154.625}, "class_id": 171, "box_caption": "hand 0.119", "scores": {"class_score": 0.119384765625}, "domain": "pixel"}, {"position": {"minX": 35.0, "minY": 52.5, "maxX": 625.0, "maxY": 203.125}, "class_id": 35, "box_caption": "table 0.119", "scores": {"class_score": 0.119384765625}, "domain": "pixel"}, {"position": {"minX": 561.0, "minY": 61.78125, "maxX": 620.0, "maxY": 156.125}, "class_id": 235, "box_caption": "cellphone 0.105", "scores": {"class_score": 0.1046142578125}, "domain": "pixel"}, {"position": {"minX": 509.5, "minY": 60.03125, "maxX": 563.5, "maxY": 150.75}, "class_id": 442, "box_caption": "mouse 0.104", "scores": {"class_score": 0.10406494140625}, "domain": "pixel"}, {"position": {"minX": 561.0, "minY": 61.78125, "maxX": 620.0, "maxY": 156.125}, "class_id": 377, "box_caption": "cell phone 0.103", "scores": {"class_score": 0.10321044921875}, "domain": "pixel"}, {"position": {"minX": 509.5, "minY": 60.03125, "maxX": 563.5, "maxY": 150.75}, "class_id": 235, "box_caption": "cellphone 0.094", "scores": {"class_score": 0.09442138671875}, "domain": "pixel"}, {"position": {"minX": 160.25, "minY": 112.375, "maxX": 225.25, "maxY": 167.125}, "class_id": 60, "box_caption": "phone 0.094", "scores": {"class_score": 0.09429931640625}, "domain": "pixel"}, {"position": {"minX": 509.5, "minY": 60.03125, "maxX": 563.5, "maxY": 150.75}, "class_id": 377, "box_caption": "cell phone 0.091", "scores": {"class_score": 0.09112548828125}, "domain": "pixel"}, {"position": {"minX": 507.0, "minY": 59.28125, "maxX": 565.0, "maxY": 149.25}, "class_id": 171, "box_caption": "hand 0.087", "scores": {"class_score": 0.08740234375}, "domain": "pixel"}, {"position": {"minX": 366.75, "minY": 89.0, "maxX": 393.25, "maxY": 112.625}, "class_id": 60, "box_caption": "phone 0.082", "scores": {"class_score": 0.08203125}, "domain": "pixel"}, {"position": {"minX": 26.1875, "minY": 40.96875, "maxX": 113.8125, "maxY": 135.625}, "class_id": 242, "box_caption": "laptop 0.081", "scores": {"class_score": 0.08050537109375}, "domain": "pixel"}, {"position": {"minX": 512.0, "minY": 61.59375, "maxX": 614.0, "maxY": 152.625}, "class_id": 442, "box_caption": "mouse 0.079", "scores": {"class_score": 0.07940673828125}, "domain": "pixel"}, {"position": {"minX": 162.5, "minY": 60.25, "maxX": 231.5, "maxY": 168.875}, "class_id": 235, "box_caption": "cellphone 0.079", "scores": {"class_score": 0.07879638671875}, "domain": "pixel"}, {"position": {"minX": 296.25, "minY": 51.15625, "maxX": 354.75, "maxY": 149.375}, "class_id": 60, "box_caption": "phone 0.078", "scores": {"class_score": 0.0784912109375}, "domain": "pixel"}, {"position": {"minX": 459.0, "minY": 53.40625, "maxX": 509.0, "maxY": 149.625}, "class_id": 243, "box_caption": "button 0.076", "scores": {"class_score": 0.07568359375}, "domain": "pixel"}, {"position": {"minX": 177.625, "minY": 114.8125, "maxX": 212.875, "maxY": 131.25}, "class_id": 60, "box_caption": "phone 0.075", "scores": {"class_score": 0.0748291015625}, "domain": "pixel"}, {"position": {"minX": 312.0, "minY": 90.9375, "maxX": 336.0, "maxY": 116.3125}, "class_id": 243, "box_caption": "button 0.073", "scores": {"class_score": 0.0728759765625}, "domain": "pixel"}, {"position": {"minX": 536.0, "minY": 115.0625, "maxX": 549.0, "maxY": 127.1875}, "class_id": 243, "box_caption": "button 0.073", "scores": {"class_score": 0.0726318359375}, "domain": "pixel"}, {"position": {"minX": 169.5, "minY": 63.3125, "maxX": 227.0, "maxY": 117.1875}, "class_id": 60, "box_caption": "phone 0.071", "scores": {"class_score": 0.0711669921875}, "domain": "pixel"}, {"position": {"minX": 354.5, "minY": 54.8125, "maxX": 408.0, "maxY": 160.25}, "class_id": 235, "box_caption": "cellphone 0.070", "scores": {"class_score": 0.07012939453125}, "domain": "pixel"}, {"position": {"minX": 162.5, "minY": 60.25, "maxX": 231.5, "maxY": 168.875}, "class_id": 377, "box_caption": "cell phone 0.066", "scores": {"class_score": 0.06634521484375}, "domain": "pixel"}, {"position": {"minX": 592.5, "minY": 130.375, "maxX": 608.5, "maxY": 141.875}, "class_id": 243, "box_caption": "button 0.066", "scores": {"class_score": 0.066162109375}, "domain": "pixel"}, {"position": {"minX": 96.0625, "minY": 52.15625, "maxX": 179.0, "maxY": 150.0}, "class_id": 242, "box_caption": "laptop 0.066", "scores": {"class_score": 0.065673828125}, "domain": "pixel"}, {"position": {"minX": 28.125, "minY": 35.46875, "maxX": 121.875, "maxY": 134.5}, "class_id": 244, "box_caption": "screen 0.065", "scores": {"class_score": 0.06488037109375}, "domain": "pixel"}, {"position": {"minX": 476.5, "minY": 99.25, "maxX": 492.0, "maxY": 112.125}, "class_id": 243, "box_caption": "button 0.063", "scores": {"class_score": 0.06317138671875}, "domain": "pixel"}, {"position": {"minX": 100.375, "minY": 55.625, "maxX": 175.375, "maxY": 158.75}, "class_id": 235, "box_caption": "cellphone 0.061", "scores": {"class_score": 0.061492919921875}, "domain": "pixel"}, {"position": {"minX": 31.84375, "minY": 33.21875, "maxX": 118.375, "maxY": 142.0}, "class_id": 377, "box_caption": "cell phone 0.061", "scores": {"class_score": 0.060882568359375}, "domain": "pixel"}, {"position": {"minX": 587.5, "minY": 129.75, "maxX": 610.5, "maxY": 143.25}, "class_id": 243, "box_caption": "button 0.060", "scores": {"class_score": 0.060302734375}, "domain": "pixel"}, {"position": {"minX": 512.0, "minY": 61.59375, "maxX": 614.0, "maxY": 152.625}, "class_id": 377, "box_caption": "cell phone 0.059", "scores": {"class_score": 0.059478759765625}, "domain": "pixel"}, {"position": {"minX": 409.0, "minY": 55.46875, "maxX": 458.5, "maxY": 155.0}, "class_id": 235, "box_caption": "cellphone 0.058", "scores": {"class_score": 0.058380126953125}, "domain": "pixel"}, {"position": {"minX": 78.625, "minY": 43.65625, "maxX": 94.125, "maxY": 53.59375}, "class_id": 243, "box_caption": "button 0.058", "scores": {"class_score": 0.057952880859375}, "domain": "pixel"}, {"position": {"minX": 99.625, "minY": 53.3125, "maxX": 174.375, "maxY": 155.0}, "class_id": 377, "box_caption": "cell phone 0.058", "scores": {"class_score": 0.05755615234375}, "domain": "pixel"}, {"position": {"minX": 31.84375, "minY": 33.21875, "maxX": 118.375, "maxY": 142.0}, "class_id": 235, "box_caption": "cellphone 0.057", "scores": {"class_score": 0.05731201171875}, "domain": "pixel"}, {"position": {"minX": 338.0, "minY": 97.9375, "maxX": 347.0, "maxY": 109.1875}, "class_id": 243, "box_caption": "button 0.057", "scores": {"class_score": 0.05718994140625}, "domain": "pixel"}, {"position": {"minX": 121.5, "minY": 133.875, "maxX": 138.0, "maxY": 146.375}, "class_id": 243, "box_caption": "button 0.056", "scores": {"class_score": 0.05615234375}, "domain": "pixel"}, {"position": {"minX": 223.25, "minY": 58.25, "maxX": 299.25, "maxY": 161.875}, "class_id": 235, "box_caption": "cellphone 0.056", "scores": {"class_score": 0.05609130859375}, "domain": "pixel"}, {"position": {"minX": 457.0, "minY": 51.5625, "maxX": 513.0, "maxY": 150.75}, "class_id": 442, "box_caption": "mouse 0.056", "scores": {"class_score": 0.055938720703125}, "domain": "pixel"}, {"position": {"minX": 564.5, "minY": 74.9375, "maxX": 615.5, "maxY": 129.0}, "class_id": 60, "box_caption": "phone 0.055", "scores": {"class_score": 0.054534912109375}, "domain": "pixel"}, {"position": {"minX": 471.0, "minY": 90.5625, "maxX": 497.5, "maxY": 121.6875}, "class_id": 243, "box_caption": "button 0.054", "scores": {"class_score": 0.053680419921875}, "domain": "pixel"}, {"position": {"minX": 174.5, "minY": 91.5, "maxX": 219.75, "maxY": 147.75}, "class_id": 60, "box_caption": "phone 0.053", "scores": {"class_score": 0.052520751953125}, "domain": "pixel"}, {"position": {"minX": 164.25, "minY": 61.875, "maxX": 229.0, "maxY": 173.875}, "class_id": 442, "box_caption": "mouse 0.052", "scores": {"class_score": 0.05181884765625}, "domain": "pixel"}, {"position": {"minX": -9.5, "minY": -3.5625, "maxX": 674.0, "maxY": 214.5}, "class_id": 35, "box_caption": "table 0.051", "scores": {"class_score": 0.050628662109375}, "domain": "pixel"}, {"position": {"minX": 406.5, "minY": 53.0625, "maxX": 457.5, "maxY": 153.75}, "class_id": 171, "box_caption": "hand 0.050", "scores": {"class_score": 0.04998779296875}, "domain": "pixel"}, {"position": {"minX": 225.375, "minY": 57.8125, "maxX": 298.0, "maxY": 161.0}, "class_id": 377, "box_caption": "cell phone 0.050", "scores": {"class_score": 0.049896240234375}, "domain": "pixel"}, {"position": {"minX": 31.90625, "minY": 32.46875, "maxX": 118.0, "maxY": 140.5}, "class_id": 171, "box_caption": "hand 0.050", "scores": {"class_score": 0.049896240234375}, "domain": "pixel"}, {"position": {"minX": 335.25, "minY": 97.375, "maxX": 349.25, "maxY": 110.625}, "class_id": 243, "box_caption": "button 0.049", "scores": {"class_score": 0.049163818359375}, "domain": "pixel"}, {"position": {"minX": 164.75, "minY": 121.5625, "maxX": 224.75, "maxY": 164.5}, "class_id": 243, "box_caption": "button 0.049", "scores": {"class_score": 0.048828125}, "domain": "pixel"}, {"position": {"minX": 24.90625, "minY": 40.0, "maxX": 115.375, "maxY": 137.0}, "class_id": 53, "box_caption": "computer 0.048", "scores": {"class_score": 0.04827880859375}, "domain": "pixel"}, {"position": {"minX": 457.0, "minY": 51.5625, "maxX": 513.0, "maxY": 150.75}, "class_id": 235, "box_caption": "cellphone 0.046", "scores": {"class_score": 0.046356201171875}, "domain": "pixel"}, {"position": {"minX": 352.0, "minY": 52.3125, "maxX": 410.0, "maxY": 162.75}, "class_id": 377, "box_caption": "cell phone 0.046", "scores": {"class_score": 0.045867919921875}, "domain": "pixel"}, {"position": {"minX": 512.0, "minY": 61.59375, "maxX": 614.0, "maxY": 152.625}, "class_id": 235, "box_caption": "cellphone 0.043", "scores": {"class_score": 0.04345703125}, "domain": "pixel"}, {"position": {"minX": 352.0, "minY": 52.3125, "maxX": 410.0, "maxY": 162.75}, "class_id": 442, "box_caption": "mouse 0.043", "scores": {"class_score": 0.04315185546875}, "domain": "pixel"}, {"position": {"minX": 353.5, "minY": 55.5625, "maxX": 408.0, "maxY": 159.75}, "class_id": 171, "box_caption": "hand 0.042", "scores": {"class_score": 0.042449951171875}, "domain": "pixel"}, {"position": {"minX": 457.0, "minY": 51.5625, "maxX": 513.0, "maxY": 150.75}, "class_id": 377, "box_caption": "cell phone 0.042", "scores": {"class_score": 0.042236328125}, "domain": "pixel"}, {"position": {"minX": 161.75, "minY": 59.4375, "maxX": 231.0, "maxY": 169.0}, "class_id": 171, "box_caption": "hand 0.042", "scores": {"class_score": 0.042083740234375}, "domain": "pixel"}, {"position": {"minX": 476.25, "minY": 96.875, "maxX": 495.25, "maxY": 116.125}, "class_id": 243, "box_caption": "button 0.042", "scores": {"class_score": 0.04205322265625}, "domain": "pixel"}, {"position": {"minX": 91.75, "minY": 53.9375, "maxX": 175.5, "maxY": 156.5}, "class_id": 244, "box_caption": "screen 0.042", "scores": {"class_score": 0.0419921875}, "domain": "pixel"}, {"position": {"minX": 57.8125, "minY": 38.1875, "maxX": 228.25, "maxY": 169.5}, "class_id": 60, "box_caption": "phone 0.041", "scores": {"class_score": 0.041168212890625}, "domain": "pixel"}, {"position": {"minX": 462.75, "minY": 63.75, "maxX": 501.75, "maxY": 99.875}, "class_id": 60, "box_caption": "phone 0.041", "scores": {"class_score": 0.0411376953125}, "domain": "pixel"}, {"position": {"minX": 409.0, "minY": 55.46875, "maxX": 458.5, "maxY": 155.0}, "class_id": 377, "box_caption": "cell phone 0.041", "scores": {"class_score": 0.041015625}, "domain": "pixel"}, {"position": {"minX": 31.03125, "minY": 35.53125, "maxX": 117.5, "maxY": 138.125}, "class_id": 442, "box_caption": "mouse 0.041", "scores": {"class_score": 0.040985107421875}, "domain": "pixel"}, {"position": {"minX": 164.875, "minY": 122.3125, "maxX": 222.625, "maxY": 165.25}, "class_id": 444, "box_caption": "key 0.041", "scores": {"class_score": 0.04095458984375}, "domain": "pixel"}, {"position": {"minX": 223.375, "minY": 58.5625, "maxX": 297.0, "maxY": 161.75}, "class_id": 171, "box_caption": "hand 0.040", "scores": {"class_score": 0.040130615234375}, "domain": "pixel"}, {"position": {"minX": 162.625, "minY": 120.875, "maxX": 225.875, "maxY": 166.625}, "class_id": 58, "box_caption": "keyboard 0.040", "scores": {"class_score": 0.0399169921875}, "domain": "pixel"}, {"position": {"minX": 454.25, "minY": 50.5625, "maxX": 512.5, "maxY": 149.75}, "class_id": 171, "box_caption": "hand 0.040", "scores": {"class_score": 0.03961181640625}, "domain": "pixel"}, {"position": {"minX": 297.75, "minY": 77.375, "maxX": 350.25, "maxY": 145.125}, "class_id": 243, "box_caption": "button 0.039", "scores": {"class_score": 0.038970947265625}, "domain": "pixel"}, {"position": {"minX": 511.5, "minY": 62.25, "maxX": 614.5, "maxY": 150.875}, "class_id": 171, "box_caption": "hand 0.039", "scores": {"class_score": 0.038909912109375}, "domain": "pixel"}, {"position": {"minX": 98.625, "minY": 54.65625, "maxX": 176.125, "maxY": 156.375}, "class_id": 171, "box_caption": "hand 0.039", "scores": {"class_score": 0.03887939453125}, "domain": "pixel"}, {"position": {"minX": 561.0, "minY": 61.78125, "maxX": 620.0, "maxY": 156.125}, "class_id": 68, "box_caption": "remote 0.038", "scores": {"class_score": 0.03790283203125}, "domain": "pixel"}, {"position": {"minX": 161.75, "minY": 60.0625, "maxX": 233.0, "maxY": 168.0}, "class_id": 242, "box_caption": "laptop 0.038", "scores": {"class_score": 0.037628173828125}, "domain": "pixel"}, {"position": {"minX": 296.5, "minY": 53.5, "maxX": 356.0, "maxY": 152.75}, "class_id": 442, "box_caption": "mouse 0.037", "scores": {"class_score": 0.036712646484375}, "domain": "pixel"}, {"position": {"minX": 97.9375, "minY": 55.65625, "maxX": 175.75, "maxY": 157.625}, "class_id": 442, "box_caption": "mouse 0.036", "scores": {"class_score": 0.0357666015625}, "domain": "pixel"}, {"position": {"minX": 160.5, "minY": 56.21875, "maxX": 234.25, "maxY": 172.875}, "class_id": 128, "box_caption": "book 0.035", "scores": {"class_score": 0.03497314453125}, "domain": "pixel"}, {"position": {"minX": 160.25, "minY": 112.375, "maxX": 225.25, "maxY": 167.125}, "class_id": 442, "box_caption": "mouse 0.034", "scores": {"class_score": 0.034393310546875}, "domain": "pixel"}, {"position": {"minX": 238.125, "minY": 113.5625, "maxX": 277.5, "maxY": 130.0}, "class_id": 60, "box_caption": "phone 0.033", "scores": {"class_score": 0.03314208984375}, "domain": "pixel"}, {"position": {"minX": 505.5, "minY": 61.09375, "maxX": 565.5, "maxY": 148.625}, "class_id": 371, "box_caption": "fork 0.033", "scores": {"class_score": 0.03271484375}, "domain": "pixel"}, {"position": {"minX": -9.5, "minY": -3.5625, "maxX": 674.0, "maxY": 214.5}, "class_id": 60, "box_caption": "phone 0.032", "scores": {"class_score": 0.032470703125}, "domain": "pixel"}, {"position": {"minX": 561.0, "minY": 61.78125, "maxX": 620.0, "maxY": 156.125}, "class_id": 154, "box_caption": "finger 0.032", "scores": {"class_score": 0.031829833984375}, "domain": "pixel"}, {"position": {"minX": 91.75, "minY": 53.9375, "maxX": 175.5, "maxY": 156.5}, "class_id": 53, "box_caption": "computer 0.031", "scores": {"class_score": 0.031402587890625}, "domain": "pixel"}, {"position": {"minX": 579.5, "minY": 85.0, "maxX": 599.5, "maxY": 100.75}, "class_id": 243, "box_caption": "button 0.031", "scores": {"class_score": 0.031280517578125}, "domain": "pixel"}, {"position": {"minX": 28.71875, "minY": 35.09375, "maxX": 121.75, "maxY": 134.875}, "class_id": 55, "box_caption": "monitor 0.031", "scores": {"class_score": 0.0306549072265625}, "domain": "pixel"}, {"position": {"minX": 296.5, "minY": 53.5, "maxX": 356.0, "maxY": 152.75}, "class_id": 235, "box_caption": "cellphone 0.030", "scores": {"class_score": 0.0302734375}, "domain": "pixel"}, {"position": {"minX": 80.5625, "minY": 41.375, "maxX": 330.75, "maxY": 176.625}, "class_id": 60, "box_caption": "phone 0.030", "scores": {"class_score": 0.0302581787109375}, "domain": "pixel"}, {"position": {"minX": 226.25, "minY": 58.71875, "maxX": 295.75, "maxY": 156.75}, "class_id": 242, "box_caption": "laptop 0.030", "scores": {"class_score": 0.0301055908203125}, "domain": "pixel"}, {"position": {"minX": 226.0, "minY": 56.71875, "maxX": 298.0, "maxY": 160.25}, "class_id": 128, "box_caption": "book 0.029", "scores": {"class_score": 0.029266357421875}, "domain": "pixel"}, {"position": {"minX": 227.5, "minY": 57.125, "maxX": 297.0, "maxY": 158.75}, "class_id": 244, "box_caption": "screen 0.029", "scores": {"class_score": 0.0290069580078125}, "domain": "pixel"}, {"position": {"minX": 162.75, "minY": 120.375, "maxX": 224.25, "maxY": 160.125}, "class_id": 198, "box_caption": "logo 0.029", "scores": {"class_score": 0.028961181640625}, "domain": "pixel"}, {"position": {"minX": 590.0, "minY": 129.125, "maxX": 609.0, "maxY": 143.625}, "class_id": 442, "box_caption": "mouse 0.029", "scores": {"class_score": 0.0285797119140625}, "domain": "pixel"}, {"position": {"minX": 409.0, "minY": 55.46875, "maxX": 458.5, "maxY": 155.0}, "class_id": 442, "box_caption": "mouse 0.028", "scores": {"class_score": 0.0284576416015625}, "domain": "pixel"}, {"position": {"minX": 568.0, "minY": 93.875, "maxX": 623.0, "maxY": 145.875}, "class_id": 60, "box_caption": "phone 0.028", "scores": {"class_score": 0.028411865234375}, "domain": "pixel"}, {"position": {"minX": 76.5625, "minY": 42.5625, "maxX": 97.1875, "maxY": 55.3125}, "class_id": 243, "box_caption": "button 0.028", "scores": {"class_score": 0.0282135009765625}, "domain": "pixel"}, {"position": {"minX": 509.5, "minY": 60.03125, "maxX": 563.5, "maxY": 150.75}, "class_id": 154, "box_caption": "finger 0.028", "scores": {"class_score": 0.02783203125}, "domain": "pixel"}, {"position": {"minX": 509.5, "minY": 60.03125, "maxX": 563.5, "maxY": 150.75}, "class_id": 68, "box_caption": "remote 0.027", "scores": {"class_score": 0.0271148681640625}, "domain": "pixel"}, {"position": {"minX": 362.25, "minY": 85.625, "maxX": 398.75, "maxY": 115.375}, "class_id": 235, "box_caption": "cellphone 0.027", "scores": {"class_score": 0.0267486572265625}, "domain": "pixel"}, {"position": {"minX": 350.75, "minY": 51.3125, "maxX": 410.25, "maxY": 159.75}, "class_id": 128, "box_caption": "book 0.027", "scores": {"class_score": 0.0267333984375}, "domain": "pixel"}, {"position": {"minX": 406.0, "minY": 52.28125, "maxX": 456.0, "maxY": 152.25}, "class_id": 371, "box_caption": "fork 0.027", "scores": {"class_score": 0.026702880859375}, "domain": "pixel"}, {"position": {"minX": 292.25, "minY": 52.6875, "maxX": 355.25, "maxY": 146.75}, "class_id": 35, "box_caption": "table 0.026", "scores": {"class_score": 0.026458740234375}, "domain": "pixel"}, {"position": {"minX": 561.0, "minY": 61.78125, "maxX": 620.0, "maxY": 156.125}, "class_id": 243, "box_caption": "button 0.026", "scores": {"class_score": 0.0263671875}, "domain": "pixel"}, {"position": {"minX": 26.4375, "minY": 35.59375, "maxX": 181.25, "maxY": 144.625}, "class_id": 60, "box_caption": "phone 0.026", "scores": {"class_score": 0.0258026123046875}, "domain": "pixel"}, {"position": {"minX": 182.0, "minY": 115.5625, "maxX": 209.75, "maxY": 129.5}, "class_id": 243, "box_caption": "button 0.025", "scores": {"class_score": 0.0252532958984375}, "domain": "pixel"}, {"position": {"minX": 362.25, "minY": 85.625, "maxX": 398.75, "maxY": 115.375}, "class_id": 153, "box_caption": "glasses 0.025", "scores": {"class_score": 0.025115966796875}, "domain": "pixel"}, {"position": {"minX": 225.0, "minY": 66.9375, "maxX": 296.0, "maxY": 130.75}, "class_id": 60, "box_caption": "phone 0.025", "scores": {"class_score": 0.0246429443359375}, "domain": "pixel"}, {"position": {"minX": 31.84375, "minY": 33.21875, "maxX": 118.375, "maxY": 142.0}, "class_id": 68, "box_caption": "remote 0.024", "scores": {"class_score": 0.024444580078125}, "domain": "pixel"}, {"position": {"minX": 511.5, "minY": 62.25, "maxX": 614.5, "maxY": 150.875}, "class_id": 68, "box_caption": "remote 0.024", "scores": {"class_score": 0.024383544921875}, "domain": "pixel"}, {"position": {"minX": 32.40625, "minY": 35.3125, "maxX": 120.375, "maxY": 141.25}, "class_id": 128, "box_caption": "book 0.024", "scores": {"class_score": 0.024322509765625}, "domain": "pixel"}, {"position": {"minX": 454.75, "minY": 49.3125, "maxX": 511.25, "maxY": 147.0}, "class_id": 371, "box_caption": "fork 0.024", "scores": {"class_score": 0.024169921875}, "domain": "pixel"}, {"position": {"minX": 167.375, "minY": 109.3125, "maxX": 224.125, "maxY": 151.0}, "class_id": 60, "box_caption": "phone 0.024", "scores": {"class_score": 0.023834228515625}, "domain": "pixel"}, {"position": {"minX": 352.0, "minY": 52.78125, "maxX": 434.5, "maxY": 151.0}, "class_id": 60, "box_caption": "phone 0.024", "scores": {"class_score": 0.0235443115234375}, "domain": "pixel"}, {"position": {"minX": 164.25, "minY": 61.875, "maxX": 229.0, "maxY": 173.875}, "class_id": 58, "box_caption": "keyboard 0.024", "scores": {"class_score": 0.023529052734375}, "domain": "pixel"}, {"position": {"minX": 555.0, "minY": 61.25, "maxX": 619.0, "maxY": 153.0}, "class_id": 371, "box_caption": "fork 0.023", "scores": {"class_score": 0.0234375}, "domain": "pixel"}, {"position": {"minX": 47.1875, "minY": 114.5625, "maxX": 84.6875, "maxY": 129.75}, "class_id": 243, "box_caption": "button 0.023", "scores": {"class_score": 0.023284912109375}, "domain": "pixel"}, {"position": {"minX": 507.0, "minY": 59.28125, "maxX": 565.0, "maxY": 149.25}, "class_id": 128, "box_caption": "book 0.023", "scores": {"class_score": 0.023193359375}, "domain": "pixel"}, {"position": {"minX": 455.0, "minY": 52.6875, "maxX": 513.0, "maxY": 149.5}, "class_id": 128, "box_caption": "book 0.023", "scores": {"class_score": 0.0230712890625}, "domain": "pixel"}, {"position": {"minX": 223.25, "minY": 58.25, "maxX": 299.25, "maxY": 161.875}, "class_id": 21, "box_caption": "cup 0.023", "scores": {"class_score": 0.0230712890625}, "domain": "pixel"}, {"position": {"minX": 162.5, "minY": 61.40625, "maxX": 232.0, "maxY": 168.125}, "class_id": 244, "box_caption": "screen 0.023", "scores": {"class_score": 0.022979736328125}, "domain": "pixel"}, {"position": {"minX": 361.25, "minY": 85.375, "maxX": 400.25, "maxY": 115.75}, "class_id": 377, "box_caption": "cell phone 0.023", "scores": {"class_score": 0.0229339599609375}, "domain": "pixel"}, {"position": {"minX": 225.375, "minY": 57.8125, "maxX": 298.0, "maxY": 161.0}, "class_id": 442, "box_caption": "mouse 0.023", "scores": {"class_score": 0.02288818359375}, "domain": "pixel"}, {"position": {"minX": 509.5, "minY": 60.03125, "maxX": 563.5, "maxY": 150.75}, "class_id": 172, "box_caption": "knife 0.023", "scores": {"class_score": 0.0228271484375}, "domain": "pixel"}, {"position": {"minX": 160.25, "minY": 112.375, "maxX": 225.25, "maxY": 167.125}, "class_id": 377, "box_caption": "cell phone 0.023", "scores": {"class_score": 0.0227508544921875}, "domain": "pixel"}, {"position": {"minX": 408.75, "minY": 53.28125, "maxX": 457.75, "maxY": 151.75}, "class_id": 172, "box_caption": "knife 0.023", "scores": {"class_score": 0.022674560546875}, "domain": "pixel"}, {"position": {"minX": 297.0, "minY": 52.9375, "maxX": 351.0, "maxY": 150.25}, "class_id": 198, "box_caption": "logo 0.023", "scores": {"class_score": 0.02252197265625}, "domain": "pixel"}, {"position": {"minX": 576.5, "minY": 89.5625, "maxX": 601.5, "maxY": 110.3125}, "class_id": 60, "box_caption": "phone 0.022", "scores": {"class_score": 0.0224609375}, "domain": "pixel"}, {"position": {"minX": 78.625, "minY": 43.65625, "maxX": 94.125, "maxY": 53.59375}, "class_id": 444, "box_caption": "key 0.022", "scores": {"class_score": 0.022430419921875}, "domain": "pixel"}, {"position": {"minX": 307.75, "minY": 83.75, "maxX": 344.75, "maxY": 120.0}, "class_id": 243, "box_caption": "button 0.022", "scores": {"class_score": 0.0223846435546875}, "domain": "pixel"}, {"position": {"minX": 118.0, "minY": 134.5, "maxX": 143.5, "maxY": 149.0}, "class_id": 243, "box_caption": "button 0.022", "scores": {"class_score": 0.0222320556640625}, "domain": "pixel"}, {"position": {"minX": 474.25, "minY": 102.4375, "maxX": 493.75, "maxY": 117.1875}, "class_id": 243, "box_caption": "button 0.022", "scores": {"class_score": 0.0221405029296875}, "domain": "pixel"}, {"position": {"minX": 164.375, "minY": 114.125, "maxX": 194.375, "maxY": 129.125}, "class_id": 60, "box_caption": "phone 0.022", "scores": {"class_score": 0.0219573974609375}, "domain": "pixel"}, {"position": {"minX": 95.8125, "minY": 53.53125, "maxX": 178.25, "maxY": 156.5}, "class_id": 55, "box_caption": "monitor 0.021", "scores": {"class_score": 0.021484375}, "domain": "pixel"}, {"position": {"minX": 169.5, "minY": 63.3125, "maxX": 227.0, "maxY": 117.1875}, "class_id": 442, "box_caption": "mouse 0.021", "scores": {"class_score": 0.0213775634765625}, "domain": "pixel"}, {"position": {"minX": 354.75, "minY": 49.96875, "maxX": 407.75, "maxY": 161.875}, "class_id": 267, "box_caption": "ear 0.021", "scores": {"class_score": 0.0213470458984375}, "domain": "pixel"}, {"position": {"minX": 101.125, "minY": 54.71875, "maxX": 177.375, "maxY": 157.875}, "class_id": 128, "box_caption": "book 0.021", "scores": {"class_score": 0.0213165283203125}, "domain": "pixel"}, {"position": {"minX": 529.5, "minY": 104.0625, "maxX": 552.5, "maxY": 134.25}, "class_id": 243, "box_caption": "button 0.021", "scores": {"class_score": 0.0212249755859375}, "domain": "pixel"}, {"position": {"minX": 161.75, "minY": 60.0625, "maxX": 233.0, "maxY": 168.0}, "class_id": 68, "box_caption": "remote 0.021", "scores": {"class_score": 0.021209716796875}, "domain": "pixel"}, {"position": {"minX": 455.25, "minY": 52.65625, "maxX": 512.0, "maxY": 149.5}, "class_id": 67, "box_caption": "paper 0.021", "scores": {"class_score": 0.0211944580078125}, "domain": "pixel"}, {"position": {"minX": 292.25, "minY": 52.6875, "maxX": 355.25, "maxY": 146.75}, "class_id": 128, "box_caption": "book 0.021", "scores": {"class_score": 0.0211944580078125}, "domain": "pixel"}, {"position": {"minX": 162.875, "minY": 106.25, "maxX": 227.375, "maxY": 162.75}, "class_id": 235, "box_caption": "cellphone 0.021", "scores": {"class_score": 0.02117919921875}, "domain": "pixel"}, {"position": {"minX": 356.0, "minY": 55.9375, "maxX": 405.0, "maxY": 153.25}, "class_id": 153, "box_caption": "glasses 0.021", "scores": {"class_score": 0.02105712890625}, "domain": "pixel"}, {"position": {"minX": 314.75, "minY": 96.1875, "maxX": 331.75, "maxY": 111.0625}, "class_id": 24, "box_caption": "knob 0.021", "scores": {"class_score": 0.0210418701171875}, "domain": "pixel"}, {"position": {"minX": 297.0, "minY": 100.75, "maxX": 347.5, "maxY": 140.75}, "class_id": 243, "box_caption": "button 0.021", "scores": {"class_score": 0.020904541015625}, "domain": "pixel"}, {"position": {"minX": 559.0, "minY": 61.40625, "maxX": 620.0, "maxY": 154.625}, "class_id": 128, "box_caption": "book 0.021", "scores": {"class_score": 0.0208892822265625}, "domain": "pixel"}, {"position": {"minX": 352.0, "minY": 52.3125, "maxX": 410.0, "maxY": 162.75}, "class_id": 172, "box_caption": "knife 0.021", "scores": {"class_score": 0.0208740234375}, "domain": "pixel"}, {"position": {"minX": 352.0, "minY": 53.75, "maxX": 408.0, "maxY": 158.75}, "class_id": 67, "box_caption": "paper 0.021", "scores": {"class_score": 0.02069091796875}, "domain": "pixel"}, {"position": {"minX": 455.0, "minY": 50.125, "maxX": 513.0, "maxY": 149.875}, "class_id": 242, "box_caption": "laptop 0.021", "scores": {"class_score": 0.0206756591796875}, "domain": "pixel"}, {"position": {"minX": 495.0, "minY": 45.375, "maxX": 633.0, "maxY": 162.625}, "class_id": 60, "box_caption": "phone 0.021", "scores": {"class_score": 0.020538330078125}, "domain": "pixel"}, {"position": {"minX": 99.125, "minY": 52.375, "maxX": 175.125, "maxY": 153.0}, "class_id": 68, "box_caption": "remote 0.021", "scores": {"class_score": 0.0205078125}, "domain": "pixel"}, {"position": {"minX": 27.1875, "minY": 32.125, "maxX": 164.5, "maxY": 150.625}, "class_id": 242, "box_caption": "laptop 0.020", "scores": {"class_score": 0.020416259765625}, "domain": "pixel"}, {"position": {"minX": 312.0, "minY": 90.9375, "maxX": 336.0, "maxY": 116.3125}, "class_id": 442, "box_caption": "mouse 0.020", "scores": {"class_score": 0.020355224609375}, "domain": "pixel"}, {"position": {"minX": 366.75, "minY": 89.0, "maxX": 393.25, "maxY": 112.625}, "class_id": 243, "box_caption": "button 0.020", "scores": {"class_score": 0.0203399658203125}, "domain": "pixel"}, {"position": {"minX": 352.0, "minY": 54.5, "maxX": 409.5, "maxY": 161.625}, "class_id": 198, "box_caption": "logo 0.020", "scores": {"class_score": 0.0203399658203125}, "domain": "pixel"}, {"position": {"minX": 353.5, "minY": 55.5625, "maxX": 408.0, "maxY": 159.75}, "class_id": 154, "box_caption": "finger 0.020", "scores": {"class_score": 0.02020263671875}, "domain": "pixel"}, {"position": {"minX": 164.25, "minY": 61.875, "maxX": 229.0, "maxY": 173.875}, "class_id": 243, "box_caption": "button 0.020", "scores": {"class_score": 0.0200958251953125}, "domain": "pixel"}, {"position": {"minX": 308.0, "minY": 95.1875, "maxX": 334.0, "maxY": 113.1875}, "class_id": 243, "box_caption": "button 0.020", "scores": {"class_score": 0.0199127197265625}, "domain": "pixel"}, {"position": {"minX": 557.5, "minY": 59.78125, "maxX": 622.5, "maxY": 155.0}, "class_id": 198, "box_caption": "logo 0.020", "scores": {"class_score": 0.0198974609375}, "domain": "pixel"}, {"position": {"minX": 174.0, "minY": 115.125, "maxX": 204.0, "maxY": 128.75}, "class_id": 243, "box_caption": "button 0.020", "scores": {"class_score": 0.019866943359375}, "domain": "pixel"}, {"position": {"minX": 569.5, "minY": 74.8125, "maxX": 609.5, "maxY": 113.1875}, "class_id": 243, "box_caption": "button 0.020", "scores": {"class_score": 0.0197601318359375}, "domain": "pixel"}, {"position": {"minX": 299.5, "minY": 53.0625, "maxX": 353.5, "maxY": 149.0}, "class_id": 377, "box_caption": "cell phone 0.020", "scores": {"class_score": 0.019683837890625}, "domain": "pixel"}, {"position": {"minX": 412.5, "minY": 54.875, "maxX": 455.5, "maxY": 124.25}, "class_id": 60, "box_caption": "phone 0.020", "scores": {"class_score": 0.019622802734375}, "domain": "pixel"}, {"position": {"minX": 366.75, "minY": 89.0, "maxX": 393.25, "maxY": 112.625}, "class_id": 117, "box_caption": "ring 0.020", "scores": {"class_score": 0.0195770263671875}, "domain": "pixel"}, {"position": {"minX": 454.25, "minY": 50.5625, "maxX": 512.5, "maxY": 149.75}, "class_id": 68, "box_caption": "remote 0.020", "scores": {"class_score": 0.0195465087890625}, "domain": "pixel"}, {"position": {"minX": 573.0, "minY": 82.25, "maxX": 606.0, "maxY": 105.0}, "class_id": 243, "box_caption": "button 0.020", "scores": {"class_score": 0.01953125}, "domain": "pixel"}, {"position": {"minX": 162.5, "minY": 60.25, "maxX": 231.5, "maxY": 168.875}, "class_id": 154, "box_caption": "finger 0.020", "scores": {"class_score": 0.019500732421875}, "domain": "pixel"}, {"position": {"minX": 409.0, "minY": 55.46875, "maxX": 458.5, "maxY": 155.0}, "class_id": 154, "box_caption": "finger 0.019", "scores": {"class_score": 0.0194549560546875}, "domain": "pixel"}, {"position": {"minX": 509.5, "minY": 60.03125, "maxX": 563.5, "maxY": 150.75}, "class_id": 243, "box_caption": "button 0.019", "scores": {"class_score": 0.019439697265625}, "domain": "pixel"}, {"position": {"minX": 31.84375, "minY": 33.21875, "maxX": 118.375, "maxY": 142.0}, "class_id": 154, "box_caption": "finger 0.019", "scores": {"class_score": 0.0194244384765625}, "domain": "pixel"}, {"position": {"minX": 455.25, "minY": 52.65625, "maxX": 512.0, "maxY": 149.5}, "class_id": 120, "box_caption": "tag 0.019", "scores": {"class_score": 0.01934814453125}, "domain": "pixel"}, {"position": {"minX": 506.5, "minY": 61.65625, "maxX": 566.5, "maxY": 150.0}, "class_id": 67, "box_caption": "paper 0.019", "scores": {"class_score": 0.0191650390625}, "domain": "pixel"}, {"position": {"minX": 27.40625, "minY": 37.8125, "maxX": 121.875, "maxY": 137.75}, "class_id": 63, "box_caption": "television 0.019", "scores": {"class_score": 0.019073486328125}, "domain": "pixel"}, {"position": {"minX": 33.0625, "minY": 36.1875, "maxX": 116.4375, "maxY": 142.5}, "class_id": 58, "box_caption": "keyboard 0.019", "scores": {"class_score": 0.0190582275390625}, "domain": "pixel"}, {"position": {"minX": 23.6875, "minY": 68.6875, "maxX": 112.8125, "maxY": 140.5}, "class_id": 60, "box_caption": "phone 0.019", "scores": {"class_score": 0.01904296875}, "domain": "pixel"}, {"position": {"minX": 166.25, "minY": 114.5625, "maxX": 192.25, "maxY": 128.25}, "class_id": 243, "box_caption": "button 0.019", "scores": {"class_score": 0.0189208984375}, "domain": "pixel"}, {"position": {"minX": 161.0, "minY": 63.0625, "maxX": 231.25, "maxY": 169.5}, "class_id": 198, "box_caption": "logo 0.019", "scores": {"class_score": 0.0189208984375}, "domain": "pixel"}, {"position": {"minX": 109.0, "minY": 31.5, "maxX": 438.0, "maxY": 185.0}, "class_id": 60, "box_caption": "phone 0.019", "scores": {"class_score": 0.018707275390625}, "domain": "pixel"}, {"position": {"minX": 48.25, "minY": 17.375, "maxX": 558.0, "maxY": 172.875}, "class_id": 35, "box_caption": "table 0.019", "scores": {"class_score": 0.0186920166015625}, "domain": "pixel"}, {"position": {"minX": 406.0, "minY": 52.28125, "maxX": 456.0, "maxY": 152.25}, "class_id": 128, "box_caption": "book 0.019", "scores": {"class_score": 0.01861572265625}, "domain": "pixel"}, {"position": {"minX": 422.5, "minY": 52.28125, "maxX": 515.5, "maxY": 149.25}, "class_id": 377, "box_caption": "cell phone 0.019", "scores": {"class_score": 0.0185546875}, "domain": "pixel"}, {"position": {"minX": 505.5, "minY": 61.09375, "maxX": 565.5, "maxY": 148.625}, "class_id": 21, "box_caption": "cup 0.019", "scores": {"class_score": 0.0185394287109375}, "domain": "pixel"}, {"position": {"minX": 351.75, "minY": 54.03125, "maxX": 409.75, "maxY": 161.75}, "class_id": 21, "box_caption": "cup 0.018", "scores": {"class_score": 0.018280029296875}, "domain": "pixel"}, {"position": {"minX": 349.75, "minY": 53.6875, "maxX": 407.25, "maxY": 156.5}, "class_id": 371, "box_caption": "fork 0.018", "scores": {"class_score": 0.018218994140625}, "domain": "pixel"}, {"position": {"minX": 561.0, "minY": 61.78125, "maxX": 620.0, "maxY": 156.125}, "class_id": 172, "box_caption": "knife 0.018", "scores": {"class_score": 0.0178375244140625}, "domain": "pixel"}, {"position": {"minX": 559.0, "minY": 61.5, "maxX": 623.0, "maxY": 155.0}, "class_id": 120, "box_caption": "tag 0.018", "scores": {"class_score": 0.0178070068359375}, "domain": "pixel"}, {"position": {"minX": 555.5, "minY": 61.03125, "maxX": 620.5, "maxY": 154.25}, "class_id": 67, "box_caption": "paper 0.018", "scores": {"class_score": 0.017730712890625}, "domain": "pixel"}, {"position": {"minX": -9.5, "minY": -3.5625, "maxX": 674.0, "maxY": 214.5}, "class_id": 54, "box_caption": "desk 0.018", "scores": {"class_score": 0.0177154541015625}, "domain": "pixel"}, {"position": {"minX": 168.0, "minY": 79.375, "maxX": 235.0, "maxY": 152.75}, "class_id": 60, "box_caption": "phone 0.018", "scores": {"class_score": 0.017547607421875}, "domain": "pixel"}, {"position": {"minX": 160.25, "minY": 62.0625, "maxX": 232.25, "maxY": 169.25}, "class_id": 120, "box_caption": "tag 0.017", "scores": {"class_score": 0.017486572265625}, "domain": "pixel"}, {"position": {"minX": 408.75, "minY": 53.28125, "maxX": 457.75, "maxY": 151.75}, "class_id": 67, "box_caption": "paper 0.017", "scores": {"class_score": 0.0174713134765625}, "domain": "pixel"}, {"position": {"minX": 57.8125, "minY": 38.1875, "maxX": 228.25, "maxY": 169.5}, "class_id": 242, "box_caption": "laptop 0.017", "scores": {"class_score": 0.0174560546875}, "domain": "pixel"}, {"position": {"minX": 508.75, "minY": 63.4375, "maxX": 565.5, "maxY": 150.25}, "class_id": 120, "box_caption": "tag 0.017", "scores": {"class_score": 0.0174102783203125}, "domain": "pixel"}, {"position": {"minX": 472.5, "minY": 95.1875, "maxX": 492.5, "maxY": 110.8125}, "class_id": 243, "box_caption": "button 0.017", "scores": {"class_score": 0.0173797607421875}, "domain": "pixel"}, {"position": {"minX": 561.0, "minY": 61.78125, "maxX": 620.0, "maxY": 156.125}, "class_id": 58, "box_caption": "keyboard 0.017", "scores": {"class_score": 0.017242431640625}, "domain": "pixel"}, {"position": {"minX": 508.75, "minY": 63.4375, "maxX": 565.5, "maxY": 150.25}, "class_id": 198, "box_caption": "logo 0.017", "scores": {"class_score": 0.0171966552734375}, "domain": "pixel"}, {"position": {"minX": 352.0, "minY": 52.3125, "maxX": 410.0, "maxY": 162.75}, "class_id": 243, "box_caption": "button 0.017", "scores": {"class_score": 0.0171966552734375}, "domain": "pixel"}, {"position": {"minX": 35.0, "minY": 52.5, "maxX": 625.0, "maxY": 203.125}, "class_id": 54, "box_caption": "desk 0.017", "scores": {"class_score": 0.0171966552734375}, "domain": "pixel"}, {"position": {"minX": 225.375, "minY": 57.8125, "maxX": 298.0, "maxY": 161.0}, "class_id": 58, "box_caption": "keyboard 0.017", "scores": {"class_score": 0.01708984375}, "domain": "pixel"}, {"position": {"minX": 411.0, "minY": 50.53125, "maxX": 460.5, "maxY": 160.875}, "class_id": 210, "box_caption": "glass 0.017", "scores": {"class_score": 0.0170440673828125}, "domain": "pixel"}, {"position": {"minX": 160.5, "minY": 61.3125, "maxX": 234.0, "maxY": 170.0}, "class_id": 53, "box_caption": "computer 0.017", "scores": {"class_score": 0.0170135498046875}, "domain": "pixel"}, {"position": {"minX": 297.0, "minY": 53.8125, "maxX": 350.5, "maxY": 149.75}, "class_id": 21, "box_caption": "cup 0.017", "scores": {"class_score": 0.0167694091796875}, "domain": "pixel"}, {"position": {"minX": 99.625, "minY": 53.3125, "maxX": 174.375, "maxY": 155.0}, "class_id": 58, "box_caption": "keyboard 0.017", "scores": {"class_score": 0.0167388916015625}, "domain": "pixel"}, {"position": {"minX": 163.0, "minY": 121.5, "maxX": 223.25, "maxY": 159.5}, "class_id": 124, "box_caption": "sticker 0.017", "scores": {"class_score": 0.016693115234375}, "domain": "pixel"}, {"position": {"minX": 519.5, "minY": 92.75, "maxX": 562.5, "maxY": 141.75}, "class_id": 243, "box_caption": "button 0.017", "scores": {"class_score": 0.01666259765625}, "domain": "pixel"}, {"position": {"minX": 56.0, "minY": 116.1875, "maxX": 78.75, "maxY": 128.25}, "class_id": 243, "box_caption": "button 0.016", "scores": {"class_score": 0.0164794921875}, "domain": "pixel"}, {"position": {"minX": 226.75, "minY": 58.21875, "maxX": 297.25, "maxY": 164.125}, "class_id": 154, "box_caption": "finger 0.016", "scores": {"class_score": 0.0164794921875}, "domain": "pixel"}, {"position": {"minX": 225.375, "minY": 57.8125, "maxX": 298.0, "maxY": 161.0}, "class_id": 67, "box_caption": "paper 0.016", "scores": {"class_score": 0.016448974609375}, "domain": "pixel"}, {"position": {"minX": 409.75, "minY": 54.0625, "maxX": 459.25, "maxY": 153.5}, "class_id": 21, "box_caption": "cup 0.016", "scores": {"class_score": 0.0164337158203125}, "domain": "pixel"}, {"position": {"minX": 338.0, "minY": 98.0, "maxX": 347.5, "maxY": 109.375}, "class_id": 442, "box_caption": "mouse 0.016", "scores": {"class_score": 0.016387939453125}, "domain": "pixel"}, {"position": {"minX": 455.25, "minY": 52.65625, "maxX": 512.0, "maxY": 149.5}, "class_id": 198, "box_caption": "logo 0.016", "scores": {"class_score": 0.016326904296875}, "domain": "pixel"}, {"position": {"minX": 57.8125, "minY": 38.1875, "maxX": 228.25, "maxY": 169.5}, "class_id": 171, "box_caption": "hand 0.016", "scores": {"class_score": 0.016326904296875}, "domain": "pixel"}, {"position": {"minX": 226.0, "minY": 56.71875, "maxX": 298.0, "maxY": 160.25}, "class_id": 68, "box_caption": "remote 0.016", "scores": {"class_score": 0.01629638671875}, "domain": "pixel"}, {"position": {"minX": 169.5, "minY": 63.3125, "maxX": 227.0, "maxY": 117.1875}, "class_id": 377, "box_caption": "cell phone 0.016", "scores": {"class_score": 0.016204833984375}, "domain": "pixel"}, {"position": {"minX": 561.0, "minY": 61.78125, "maxX": 620.0, "maxY": 156.125}, "class_id": 1, "box_caption": "handle 0.016", "scores": {"class_score": 0.0161895751953125}, "domain": "pixel"}, {"position": {"minX": 237.5, "minY": 114.6875, "maxX": 267.0, "maxY": 128.25}, "class_id": 243, "box_caption": "button 0.016", "scores": {"class_score": 0.0161285400390625}, "domain": "pixel"}, {"position": {"minX": 512.0, "minY": 61.59375, "maxX": 614.0, "maxY": 152.625}, "class_id": 154, "box_caption": "finger 0.016", "scores": {"class_score": 0.01611328125}, "domain": "pixel"}, {"position": {"minX": 223.375, "minY": 58.5625, "maxX": 297.0, "maxY": 161.75}, "class_id": 120, "box_caption": "tag 0.016", "scores": {"class_score": 0.016082763671875}, "domain": "pixel"}, {"position": {"minX": 100.375, "minY": 55.625, "maxX": 175.375, "maxY": 158.75}, "class_id": 154, "box_caption": "finger 0.016", "scores": {"class_score": 0.0160675048828125}, "domain": "pixel"}, {"position": {"minX": 457.0, "minY": 51.5625, "maxX": 513.0, "maxY": 150.75}, "class_id": 154, "box_caption": "finger 0.016", "scores": {"class_score": 0.0160675048828125}, "domain": "pixel"}, {"position": {"minX": 161.875, "minY": 98.75, "maxX": 228.375, "maxY": 165.0}, "class_id": 171, "box_caption": "hand 0.016", "scores": {"class_score": 0.0159454345703125}, "domain": "pixel"}, {"position": {"minX": 507.0, "minY": 59.28125, "maxX": 565.0, "maxY": 149.25}, "class_id": 1, "box_caption": "handle 0.016", "scores": {"class_score": 0.015869140625}, "domain": "pixel"}, {"position": {"minX": 411.0, "minY": 50.53125, "maxX": 460.5, "maxY": 160.875}, "class_id": 22, "box_caption": "bottle 0.016", "scores": {"class_score": 0.015716552734375}, "domain": "pixel"}, {"position": {"minX": 423.75, "minY": 52.21875, "maxX": 515.5, "maxY": 151.0}, "class_id": 172, "box_caption": "knife 0.016", "scores": {"class_score": 0.015716552734375}, "domain": "pixel"}, {"position": {"minX": 297.0, "minY": 104.375, "maxX": 347.5, "maxY": 141.125}, "class_id": 444, "box_caption": "key 0.016", "scores": {"class_score": 0.0157012939453125}, "domain": "pixel"}, {"position": {"minX": 160.25, "minY": 112.375, "maxX": 225.25, "maxY": 167.125}, "class_id": 128, "box_caption": "book 0.016", "scores": {"class_score": 0.015655517578125}, "domain": "pixel"}, {"position": {"minX": 29.96875, "minY": 39.90625, "maxX": 118.75, "maxY": 136.625}, "class_id": 65, "box_caption": "tv 0.016", "scores": {"class_score": 0.0156402587890625}, "domain": "pixel"}, {"position": {"minX": 455.0, "minY": 52.6875, "maxX": 513.0, "maxY": 149.5}, "class_id": 58, "box_caption": "keyboard 0.016", "scores": {"class_score": 0.015594482421875}, "domain": "pixel"}, {"position": {"minX": 293.75, "minY": 55.78125, "maxX": 353.25, "maxY": 148.125}, "class_id": 172, "box_caption": "knife 0.016", "scores": {"class_score": 0.01558685302734375}, "domain": "pixel"}, {"position": {"minX": 299.0, "minY": 53.25, "maxX": 351.5, "maxY": 150.25}, "class_id": 120, "box_caption": "tag 0.016", "scores": {"class_score": 0.01557159423828125}, "domain": "pixel"}, {"position": {"minX": 352.0, "minY": 54.5, "maxX": 409.5, "maxY": 161.625}, "class_id": 120, "box_caption": "tag 0.015", "scores": {"class_score": 0.01549530029296875}, "domain": "pixel"}, {"position": {"minX": 350.75, "minY": 51.3125, "maxX": 410.25, "maxY": 159.75}, "class_id": 58, "box_caption": "keyboard 0.015", "scores": {"class_score": 0.01548004150390625}, "domain": "pixel"}, {"position": {"minX": 422.5, "minY": 52.28125, "maxX": 515.5, "maxY": 149.25}, "class_id": 235, "box_caption": "cellphone 0.015", "scores": {"class_score": 0.0154266357421875}, "domain": "pixel"}, {"position": {"minX": 297.5, "minY": 58.125, "maxX": 350.0, "maxY": 105.625}, "class_id": 60, "box_caption": "phone 0.015", "scores": {"class_score": 0.015350341796875}, "domain": "pixel"}, {"position": {"minX": 362.25, "minY": 85.625, "maxX": 398.75, "maxY": 115.375}, "class_id": 117, "box_caption": "ring 0.015", "scores": {"class_score": 0.01519012451171875}, "domain": "pixel"}, {"position": {"minX": 160.5, "minY": 61.3125, "maxX": 234.0, "maxY": 170.0}, "class_id": 21, "box_caption": "cup 0.015", "scores": {"class_score": 0.01515960693359375}, "domain": "pixel"}, {"position": {"minX": 28.71875, "minY": 35.09375, "maxX": 121.75, "maxY": 134.875}, "class_id": 5, "box_caption": "picture 0.015", "scores": {"class_score": 0.01502227783203125}, "domain": "pixel"}, {"position": {"minX": 349.5, "minY": 52.375, "maxX": 411.0, "maxY": 163.625}, "class_id": 68, "box_caption": "remote 0.015", "scores": {"class_score": 0.01491546630859375}, "domain": "pixel"}, {"position": {"minX": 511.5, "minY": 62.25, "maxX": 614.5, "maxY": 150.875}, "class_id": 371, "box_caption": "fork 0.015", "scores": {"class_score": 0.01488494873046875}, "domain": "pixel"}, {"position": {"minX": 49.3125, "minY": 114.5625, "maxX": 82.9375, "maxY": 129.5}, "class_id": 444, "box_caption": "key 0.015", "scores": {"class_score": 0.01483917236328125}, "domain": "pixel"}, {"position": {"minX": 29.8125, "minY": 33.0625, "maxX": 160.75, "maxY": 150.0}, "class_id": 442, "box_caption": "mouse 0.015", "scores": {"class_score": 0.01483917236328125}, "domain": "pixel"}, {"position": {"minX": 338.0, "minY": 97.9375, "maxX": 347.0, "maxY": 109.1875}, "class_id": 27, "box_caption": "light 0.015", "scores": {"class_score": 0.01480865478515625}, "domain": "pixel"}, {"position": {"minX": 226.375, "minY": 118.5, "maxX": 281.75, "maxY": 150.0}, "class_id": 243, "box_caption": "button 0.015", "scores": {"class_score": 0.0147857666015625}, "domain": "pixel"}, {"position": {"minX": 39.4375, "minY": 114.0625, "maxX": 93.6875, "maxY": 131.75}, "class_id": 243, "box_caption": "button 0.015", "scores": {"class_score": 0.014678955078125}, "domain": "pixel"}, {"position": {"minX": 409.75, "minY": 54.21875, "maxX": 459.25, "maxY": 153.125}, "class_id": 198, "box_caption": "logo 0.015", "scores": {"class_score": 0.01464080810546875}, "domain": "pixel"}, {"position": {"minX": 162.5, "minY": 61.40625, "maxX": 232.0, "maxY": 168.125}, "class_id": 67, "box_caption": "paper 0.015", "scores": {"class_score": 0.0146331787109375}, "domain": "pixel"}, {"position": {"minX": 225.375, "minY": 57.8125, "maxX": 298.0, "maxY": 161.0}, "class_id": 172, "box_caption": "knife 0.015", "scores": {"class_score": 0.014556884765625}, "domain": "pixel"}, {"position": {"minX": 406.0, "minY": 52.28125, "maxX": 456.0, "maxY": 152.25}, "class_id": 68, "box_caption": "remote 0.015", "scores": {"class_score": 0.0145416259765625}, "domain": "pixel"}, {"position": {"minX": 532.5, "minY": 110.5625, "maxX": 552.5, "maxY": 128.625}, "class_id": 243, "box_caption": "button 0.015", "scores": {"class_score": 0.01450347900390625}, "domain": "pixel"}, {"position": {"minX": 457.25, "minY": 50.53125, "maxX": 511.75, "maxY": 146.125}, "class_id": 172, "box_caption": "knife 0.014", "scores": {"class_score": 0.0144500732421875}, "domain": "pixel"}, {"position": {"minX": 511.5, "minY": 62.25, "maxX": 614.5, "maxY": 150.875}, "class_id": 128, "box_caption": "book 0.014", "scores": {"class_score": 0.0142974853515625}, "domain": "pixel"}, {"position": {"minX": 299.0, "minY": 98.5625, "maxX": 313.0, "maxY": 110.9375}, "class_id": 243, "box_caption": "button 0.014", "scores": {"class_score": 0.01422119140625}, "domain": "pixel"}, {"position": {"minX": 352.5, "minY": 50.5625, "maxX": 409.5, "maxY": 166.25}, "class_id": 242, "box_caption": "laptop 0.014", "scores": {"class_score": 0.014190673828125}, "domain": "pixel"}, {"position": {"minX": 511.5, "minY": 60.78125, "maxX": 565.5, "maxY": 146.5}, "class_id": 275, "box_caption": "hands 0.014", "scores": {"class_score": 0.01409149169921875}, "domain": "pixel"}, {"position": {"minX": 506.5, "minY": 61.65625, "maxX": 566.5, "maxY": 150.0}, "class_id": 23, "box_caption": "spoon 0.014", "scores": {"class_score": 0.01399993896484375}, "domain": "pixel"}, {"position": {"minX": 169.5, "minY": 63.3125, "maxX": 227.0, "maxY": 117.1875}, "class_id": 242, "box_caption": "laptop 0.014", "scores": {"class_score": 0.01396942138671875}, "domain": "pixel"}, {"position": {"minX": 29.96875, "minY": 39.90625, "maxX": 118.75, "maxY": 136.625}, "class_id": 292, "box_caption": "cake 0.014", "scores": {"class_score": 0.0139007568359375}, "domain": "pixel"}, {"position": {"minX": 314.5, "minY": 96.0625, "maxX": 332.0, "maxY": 111.5625}, "class_id": 198, "box_caption": "logo 0.014", "scores": {"class_score": 0.01389312744140625}, "domain": "pixel"}, {"position": {"minX": 226.25, "minY": 58.71875, "maxX": 295.75, "maxY": 156.75}, "class_id": 53, "box_caption": "computer 0.014", "scores": {"class_score": 0.0138702392578125}, "domain": "pixel"}, {"position": {"minX": 453.5, "minY": 52.125, "maxX": 513.0, "maxY": 149.125}, "class_id": 21, "box_caption": "cup 0.014", "scores": {"class_score": 0.0137786865234375}, "domain": "pixel"}, {"position": {"minX": 109.625, "minY": 133.375, "maxX": 149.625, "maxY": 148.125}, "class_id": 60, "box_caption": "phone 0.014", "scores": {"class_score": 0.01375579833984375}, "domain": "pixel"}, {"position": {"minX": 79.1875, "minY": 42.75, "maxX": 93.0625, "maxY": 54.375}, "class_id": 442, "box_caption": "mouse 0.014", "scores": {"class_score": 0.01360321044921875}, "domain": "pixel"}, {"position": {"minX": 559.5, "minY": 58.875, "maxX": 623.5, "maxY": 154.625}, "class_id": 275, "box_caption": "hands 0.014", "scores": {"class_score": 0.0135650634765625}, "domain": "pixel"}, {"position": {"minX": 169.5, "minY": 63.3125, "maxX": 227.0, "maxY": 117.1875}, "class_id": 235, "box_caption": "cellphone 0.014", "scores": {"class_score": 0.0135650634765625}, "domain": "pixel"}, {"position": {"minX": -9.5, "minY": -3.5625, "maxX": 674.0, "maxY": 214.5}, "class_id": 58, "box_caption": "keyboard 0.014", "scores": {"class_score": 0.01355743408203125}, "domain": "pixel"}, {"position": {"minX": 109.625, "minY": 133.375, "maxX": 149.625, "maxY": 148.125}, "class_id": 243, "box_caption": "button 0.014", "scores": {"class_score": 0.01352691650390625}, "domain": "pixel"}, {"position": {"minX": 314.75, "minY": 96.1875, "maxX": 331.75, "maxY": 111.0625}, "class_id": 27, "box_caption": "light 0.013", "scores": {"class_score": 0.01348876953125}, "domain": "pixel"}, {"position": {"minX": 512.0, "minY": 61.59375, "maxX": 614.0, "maxY": 152.625}, "class_id": 243, "box_caption": "button 0.013", "scores": {"class_score": 0.01348876953125}, "domain": "pixel"}, {"position": {"minX": 162.5, "minY": 60.25, "maxX": 231.5, "maxY": 168.875}, "class_id": 342, "box_caption": "controller 0.013", "scores": {"class_score": 0.01316070556640625}, "domain": "pixel"}, {"position": {"minX": 117.875, "minY": 74.0625, "maxX": 231.125, "maxY": 164.0}, "class_id": 60, "box_caption": "phone 0.013", "scores": {"class_score": 0.01311492919921875}, "domain": "pixel"}, {"position": {"minX": -9.5, "minY": -3.5625, "maxX": 674.0, "maxY": 214.5}, "class_id": 242, "box_caption": "laptop 0.013", "scores": {"class_score": 0.0131072998046875}, "domain": "pixel"}, {"position": {"minX": 552.0, "minY": 62.40625, "maxX": 628.0, "maxY": 143.125}, "class_id": 153, "box_caption": "glasses 0.013", "scores": {"class_score": 0.013092041015625}, "domain": "pixel"}, {"position": {"minX": 455.25, "minY": 52.65625, "maxX": 512.0, "maxY": 149.5}, "class_id": 444, "box_caption": "key 0.013", "scores": {"class_score": 0.0130462646484375}, "domain": "pixel"}, {"position": {"minX": 561.0, "minY": 61.78125, "maxX": 620.0, "maxY": 156.125}, "class_id": 342, "box_caption": "controller 0.013", "scores": {"class_score": 0.01297760009765625}, "domain": "pixel"}, {"position": {"minX": 511.5, "minY": 60.78125, "maxX": 565.5, "maxY": 146.5}, "class_id": 242, "box_caption": "laptop 0.013", "scores": {"class_score": 0.012908935546875}, "domain": "pixel"}, {"position": {"minX": 558.0, "minY": 59.90625, "maxX": 623.0, "maxY": 154.875}, "class_id": 420, "box_caption": "camera 0.013", "scores": {"class_score": 0.01288604736328125}, "domain": "pixel"}, {"position": {"minX": 297.75, "minY": 77.375, "maxX": 350.25, "maxY": 145.125}, "class_id": 444, "box_caption": "key 0.013", "scores": {"class_score": 0.012725830078125}, "domain": "pixel"}, {"position": {"minX": 31.84375, "minY": 33.21875, "maxX": 118.375, "maxY": 142.0}, "class_id": 243, "box_caption": "button 0.013", "scores": {"class_score": 0.0127105712890625}, "domain": "pixel"}, {"position": {"minX": 162.75, "minY": 120.375, "maxX": 224.25, "maxY": 160.125}, "class_id": 281, "box_caption": "license plate 0.013", "scores": {"class_score": 0.01268768310546875}, "domain": "pixel"}, {"position": {"minX": 455.0, "minY": 52.6875, "maxX": 513.0, "maxY": 149.5}, "class_id": 124, "box_caption": "sticker 0.013", "scores": {"class_score": 0.01267242431640625}, "domain": "pixel"}, {"position": {"minX": 95.0, "minY": 56.40625, "maxX": 178.25, "maxY": 156.125}, "class_id": 63, "box_caption": "television 0.013", "scores": {"class_score": 0.01265716552734375}, "domain": "pixel"}, {"position": {"minX": 223.75, "minY": 54.6875, "maxX": 298.75, "maxY": 165.5}, "class_id": 267, "box_caption": "ear 0.013", "scores": {"class_score": 0.01265716552734375}, "domain": "pixel"}, {"position": {"minX": 362.25, "minY": 85.625, "maxX": 398.75, "maxY": 115.375}, "class_id": 243, "box_caption": "button 0.013", "scores": {"class_score": 0.01263427734375}, "domain": "pixel"}, {"position": {"minX": 95.5, "minY": 57.4375, "maxX": 174.75, "maxY": 158.5}, "class_id": 342, "box_caption": "controller 0.013", "scores": {"class_score": 0.012603759765625}, "domain": "pixel"}, {"position": {"minX": 517.0, "minY": 124.625, "maxX": 564.0, "maxY": 146.125}, "class_id": 243, "box_caption": "button 0.013", "scores": {"class_score": 0.01258087158203125}, "domain": "pixel"}, {"position": {"minX": 559.5, "minY": 58.875, "maxX": 623.5, "maxY": 154.625}, "class_id": 242, "box_caption": "laptop 0.012", "scores": {"class_score": 0.0124969482421875}, "domain": "pixel"}, {"position": {"minX": 27.1875, "minY": 32.125, "maxX": 164.5, "maxY": 150.625}, "class_id": 171, "box_caption": "hand 0.012", "scores": {"class_score": 0.01244354248046875}, "domain": "pixel"}, {"position": {"minX": 408.75, "minY": 53.28125, "maxX": 457.75, "maxY": 151.75}, "class_id": 23, "box_caption": "spoon 0.012", "scores": {"class_score": 0.01242828369140625}, "domain": "pixel"}, {"position": {"minX": 509.75, "minY": 59.6875, "maxX": 566.0, "maxY": 146.5}, "class_id": 267, "box_caption": "ear 0.012", "scores": {"class_score": 0.01239776611328125}, "domain": "pixel"}, {"position": {"minX": 509.5, "minY": 60.03125, "maxX": 563.5, "maxY": 150.75}, "class_id": 342, "box_caption": "controller 0.012", "scores": {"class_score": 0.0123748779296875}, "domain": "pixel"}, {"position": {"minX": 183.875, "minY": 113.375, "maxX": 207.625, "maxY": 128.25}, "class_id": 60, "box_caption": "phone 0.012", "scores": {"class_score": 0.01232147216796875}, "domain": "pixel"}, {"position": {"minX": 223.375, "minY": 58.5625, "maxX": 297.0, "maxY": 161.75}, "class_id": 198, "box_caption": "logo 0.012", "scores": {"class_score": 0.01232147216796875}, "domain": "pixel"}, {"position": {"minX": 422.5, "minY": 52.28125, "maxX": 515.5, "maxY": 149.25}, "class_id": 154, "box_caption": "finger 0.012", "scores": {"class_score": 0.01232147216796875}, "domain": "pixel"}], "class_labels": {"0": "lid", "1": "handle", "2": "oven", "3": "door", "4": "faucet", "5": "picture", "6": "stove", "7": "cabinet", "8": "bowl", "9": "sink", "10": "counter", "11": "kitchen", "12": "cabinets", "13": "wall", "14": "handles", "15": "rack", "16": "shelf", "17": "towel", "18": "dish", "19": "floor", "20": "tiles", "21": "cup", "22": "bottle", "23": "spoon", "24": "knob", "25": "pot", "26": "doors", "27": "light", "28": "ceiling", "29": "window", "30": "drawer", "31": "fruit", "32": "chairs", "33": "lights", "34": "chair", "35": "table", "36": "microwave", "37": "carpet", "38": "wheel", "39": "stripes", "40": "basket", "41": "bathroom", "42": "container", "43": "mirror", "44": "toilet", "45": "curtain", "46": "seat", "47": "flowers", "48": "sauce", "49": "pan", "50": "flower", "51": "leaves", "52": "food", "53": "computer", "54": "desk", "55": "monitor", "56": "box", "57": "leg", "58": "keyboard", "59": "wires", "60": "phone", "61": "frame", "62": "mug", "63": "television", "64": "suitcase", "65": "tv", "66": "stand", "67": "paper", "68": "remote", "69": "sign", "70": "shirt", "71": "bed", "72": "blanket", "73": "room", "74": "outlet", "75": "white", "76": "side", "77": "plate", "78": "tire", "79": "tile", "80": "ground", "81": "man", "82": "lines", "83": "sky", "84": "tree", "85": "roof", "86": "building", "87": "helmet", "88": "pants", "89": "foot", "90": "concrete", "91": "house", "92": "street", "93": "hair", "94": "bike", "95": "vehicle", "96": "person", "97": "motorcycle", "98": "headlight", "99": "dog", "100": "pillows", "101": "books", "102": "couch", "103": "corner", "104": "sofa", "105": "speaker", "106": "legs", "107": "head", "108": "paw", "109": "arm", "110": "cushion", "111": "jacket", "112": "coat", "113": "ski pole", "114": "a", "115": "ski", "116": "bottom", "117": "ring", "118": "letter", "119": "snow", "120": "tag", "121": "writing", "122": "skis", "123": "poles", "124": "sticker", "125": "pole", "126": "tray", "127": "bench", "128": "book", "129": "pillow", "130": "refrigerator", "131": "cheese", "132": "bar", "133": "duck", "134": "water", "135": "beak", "136": "eyes", "137": "rug", "138": "plant", "139": "bag", "140": "cord", "141": "cloth", "142": "line", "143": "this", "144": "boat", "145": "bicycle", "146": "sand", "147": "the", "148": "red", "149": "black", "150": "beach", "151": "rocks", "152": "rock", "153": "glasses", "154": "finger", "155": "woman", "156": "shoe", "157": "top", "158": "sunglasses", "159": "belt", "160": "umbrella", "161": "dress", "162": "shoes", "163": "skirt", "164": "purse", "165": "trim", "166": "tip", "167": "lady", "168": "part", "169": "shadow", "170": "shade", "171": "hand", "172": "knife", "173": "blinds", "174": "board", "175": "edge", "176": "mountain", "177": "snowboard", "178": "stick", "179": "weeds", "180": "background", "181": "hill", "182": "bear", "183": "crack", "184": "hole", "185": "teddy bear", "186": "street light", "187": "truck", "188": "cloud", "189": "plants", "190": "plane", "191": "air", "192": "road", "193": "branches", "194": "fence", "195": "distance", "196": "clouds", "197": "tail", "198": "logo", "199": "dirt", "200": "buildings", "201": "tower", "202": "car", "203": "wing", "204": "statue", "205": "grass", "206": "path", "207": "collar", "208": "body", "209": "reflection", "210": "glass", "211": "clock", "212": "holder", "213": "wood", "214": "back", "215": "jeans", "216": "sweater", "217": "strap", "218": "buttons", "219": "signs", "220": "hood", "221": "cover", "222": "pipe", "223": "windows", "224": "branch", "225": "area", "226": "brick", "227": "steps", "228": "numbers", "229": "post", "230": "pocket", "231": "backpack", "232": "luggage", "233": "metal", "234": "bolt", "235": "cellphone", "236": "painting", "237": "eye", "238": "sock", "239": "bat", "240": "object", "241": "lamp", "242": "laptop", "243": "button", "244": "screen", "245": "fur", "246": "jar", "247": "vase", "248": "words", "249": "trash can", "250": "vegetables", "251": "bridge", "252": "candle", "253": "wire", "254": "rope", "255": "cart", "256": "train car", "257": "train", "258": "chain", "259": "paint", "260": "guy", "261": "watch", "262": "wrist", "263": "men", "264": "t-shirt", "265": "boy", "266": "shorts", "267": "ear", "268": "people", "269": "knee", "270": "bus", "271": "blue", "272": "stripe", "273": "onion", "274": "bucket", "275": "hands", "276": "curtains", "277": "cap", "278": "sidewalk", "279": "flag", "280": "pavement", "281": "license plate", "282": "ball", "283": "racket", "284": "rail", "285": "stem", "286": "leaf", "287": "headlights", "288": "photo", "289": "number", "290": "letters", "291": "curb", "292": "cake", "293": "hat", "294": "front", "295": "patch", "296": "elephant", "297": "trunk", "298": "feet", "299": "cat", "300": "whiskers", "301": "face", "302": "nose", "303": "windshield", "304": "wheels", "305": "banner", "306": "city", "307": "neck", "308": "tie", "309": "clothes", "310": "ripples", "311": "bricks", "312": "sun", "313": "skier", "314": "trees", "315": "animal", "316": "surface", "317": "birds", "318": "ocean", "319": "mouth", "320": "gate", "321": "bracelet", "322": "player", "323": "court", "324": "spectator", "325": "tennis racket", "326": "circle", "327": "chimney", "328": "structure", "329": "shore", "330": "river", "331": "stone", "332": "girl", "333": "horse", "334": "sneakers", "335": "jet", "336": "runway", "337": "field", "338": "airplane", "339": "skateboard", "340": "sneaker", "341": "surfboard", "342": "controller", "343": "bird", "344": "engine", "345": "cone", "346": "stairs", "347": "ramp", "348": "skateboarder", "349": "zebra", "350": "mane", "351": "hoof", "352": "poster", "353": "sleeve", "354": "bushes", "355": "kite", "356": "child", "357": "park", "358": "cow", "359": "cows", "360": "socks", "361": "horn", "362": "name", "363": "wave", "364": "waves", "365": "van", "366": "tablecloth", "367": "giraffe", "368": "design", "369": "vest", "370": "lettuce", "371": "fork", "372": "napkin", "373": "meat", "374": "sandwich", "375": "bun", "376": "wine", "377": "cell phone", "378": "banana", "379": "tomato", "380": "bananas", "381": "pizza", "382": "tent", "383": "walkway", "384": "word", "385": "can", "386": "carrot", "387": "spots", "388": "lettering", "389": "orange", "390": "slice", "391": "bread", "392": "baby", "393": "suit", "394": "broccoli", "395": "kid", "396": "beard", "397": "pepper", "398": "crust", "399": "label", "400": "net", "401": "scarf", "402": "pen", "403": "shoulder", "404": "pattern", "405": "vegetable", "406": "column", "407": "base", "408": "platform", "409": "hot dog", "410": "spot", "411": "batter", "412": "glove", "413": "catcher", "414": "umpire", "415": "jersey", "416": "baseball", "417": "uniform", "418": "gloves", "419": "band", "420": "camera", "421": "tennis court", "422": "boots", "423": "string", "424": "railing", "425": "ears", "426": "tennis ball", "427": "log", "428": "boot", "429": "track", "430": "shadows", "431": "frisbee", "432": "arms", "433": "panel", "434": "graffiti", "435": "elephants", "436": "tracks", "437": "horses", "438": "cars", "439": "apple", "440": "bush", "441": "pillar", "442": "mouse", "443": "goggles", "444": "key", "445": "tree trunk", "446": "doorway", "447": "star", "448": "street sign", "449": "traffic light", "450": "boats", "451": "mountains", "452": "stop sign", "453": "balcony", "454": "awning", "455": "fire hydrant", "456": "hydrant", "457": "arrow", "458": "train tracks", "459": "surfer", "460": "giraffes", "461": "palm tree", "462": "gravel", "463": "wetsuit", "464": "horns", "465": "zebras", "466": "sheep", "467": "necklace", "468": "tusk", "469": "square", "470": "donut"}}